[{"id":"visual.root.session.visual.emitter.list[1201].count","lb":"count","tp":"obj","ch":[{"id":"visual.root.session.visual.emitter.list[1201].count.min","lb":"min: 6","tp":"num","cb":"b198"},{"id":"visual.root.session.visual.emitter.list[1201].count.range","lb":"range: 3","tp":"num","cb":"b198"}],"cb":"b198"},{"id":"visual.root.session.visual.emitter.list[1201].directionDeviation","lb":"directionDeviation: 0.0","tp":"num","cb":"b198"},{"id":"visual.root.session.visual.emitter.list[1201].dispersion","lb":"dispersion","tp":"obj","ch":[{"id":"visual.root.session.visual.emitter.list[1201].dispersion.min","lb":"min: 0.800000011920929","tp":"num","cb":"b198"},{"id":"visual.root.session.visual.emitter.list[1201].dispersion.range","lb":"range: 0.6000000238418579","tp":"num","cb":"b198"}],"cb":"b198"},{"id":"visual.root.session.visual.emitter.list[1201].emitOnSphere","lb":"emitOnSphere: true","tp":"bool","cb":"b198"},{"id":"visual.root.session.visual.emitter.list[1201].externalSpeed","lb":"externalSpeed","tp":"obj","ch":[{"id":"visual.root.session.visual.emitter.list[1201].externalSpeed.min","lb":"min: 0.0","tp":"num","cb":"b198"},{"id":"visual.root.session.visual.emitter.list[1201].externalSpeed.range","lb":"range: 0.0","tp":"num","cb":"b198"}],"cb":"b198"},{"id":"visual.root.session.visual.emitter.list[1201].particle","lb":"particle: 1172","tp":"num","cb":"b198"},{"id":"visual.root.session.visual.emitter.list[1201].radius","lb":"radius: 10.0","tp":"num","cb":"b198"},{"id":"visual.root.session.visual.emitter.list[1201].scale","lb":"scale","tp":"obj","ch":[{"id":"visual.root.session.visual.emitter.list[1201].scale.min","lb":"min: 0.15000000596046448","tp":"num","cb":"b198"},{"id":"visual.root.session.visual.emitter.list[1201].scale.range","lb":"range: 0.05000000074505806","tp":"num","cb":"b198"}],"cb":"b198"},{"id":"visual.root.session.visual.emitter.list[1201].speed","lb":"speed","tp":"obj","ch":[{"id":"visual.root.session.visual.emitter.list[1201].speed.min","lb":"min: 8.0","tp":"num","cb":"b198"},{"id":"visual.root.session.visual.emitter.list[1201].speed.range","lb":"range: 4.0","tp":"num","cb":"b198"}],"cb":"b198"},{"id":"visual.root.session.visual.emitter.list[1201].waterAlternative","lb":"waterAlternative: 1222","tp":"num","cb":"b198"}]