[{"id":"visual.root.session.visual.emitter.groups[1422].f_clear","lb":"f_clear()","tp":"func","cb":"b193"},{"id":"visual.root.session.visual.emitter.groups[1422].f_copy","lb":"f_copy(fromId, toId)","tp":"func","cb":"b193"},{"id":"visual.root.session.visual.emitter.groups[1422].f_create","lb":"f_create()","tp":"func","cb":"b193"},{"id":"visual.root.session.visual.emitter.groups[1422].f_remove","lb":"f_remove(id)","tp":"func","cb":"b193"},{"id":"visual.root.session.visual.emitter.groups[1422].size","lb":"size: 38","tp":"num","cb":"b193"},{"id":"visual.root.session.visual.emitter.groups[1422].0","lb":"0","tp":"obj","ch":[{"id":"visual.root.session.visual.emitter.groups[1422].0.displacement","lb":"displacement","tp":"obj","ch":[{"id":"visual.root.session.visual.emitter.groups[1422].0.displacement.length","lb":"length: 0.0","tp":"num","cb":"b193"},{"id":"visual.root.session.visual.emitter.groups[1422].0.displacement.x","lb":"x: 0.0","tp":"num","cb":"b193"},{"id":"visual.root.session.visual.emitter.groups[1422].0.displacement.y","lb":"y: 0.0","tp":"num","cb":"b193"},{"id":"visual.root.session.visual.emitter.groups[1422].0.displacement.z","lb":"z: 0.0","tp":"num","cb":"b193"}],"cb":"b193"},{"id":"visual.root.session.visual.emitter.groups[1422].0.link","lb":"link: 896","tp":"num","cb":"b193"},{"id":"visual.root.session.visual.emitter.groups[1422].0.scale","lb":"scale: 5.0","tp":"num","cb":"b193"},{"id":"visual.root.session.visual.emitter.groups[1422].0.toEmitter","lb":"toEmitter: true","tp":"bool","cb":"b193"}],"cb":"b193"},{"id":"visual.root.session.visual.emitter.groups[1422].1","lb":"1","tp":"obj","ch":[{"id":"visual.root.session.visual.emitter.groups[1422].1.displacement","lb":"displacement","tp":"obj","ch":[{"id":"visual.root.session.visual.emitter.groups[1422].1.displacement.length","lb":"length: 0.0","tp":"num","cb":"b193"},{"id":"visual.root.session.visual.emitter.groups[1422].1.displacement.x","lb":"x: 0.0","tp":"num","cb":"b193"},{"id":"visual.root.session.visual.emitter.groups[1422].1.displacement.y","lb":"y: 0.0","tp":"num","cb":"b193"},{"id":"visual.root.session.visual.emitter.groups[1422].1.displacement.z","lb":"z: 0.0","tp":"num","cb":"b193"}],"cb":"b193"},{"id":"visual.root.session.visual.emitter.groups[1422].1.link","lb":"link: 642","tp":"num","cb":"b193"},{"id":"visual.root.session.visual.emitter.groups[1422].1.scale","lb":"scale: 0.699999988079071","tp":"num","cb":"b193"},{"id":"visual.root.session.visual.emitter.groups[1422].1.toEmitter","lb":"toEmitter: true","tp":"bool","cb":"b193"}],"cb":"b193"},{"id":"visual.root.session.visual.emitter.groups[1422].2","lb":"2","tp":"obj","ch":[{"id":"visual.root.session.visual.emitter.groups[1422].2.displacement","lb":"displacement","tp":"obj","ch":[{"id":"visual.root.session.visual.emitter.groups[1422].2.displacement.length","lb":"length: 0.0","tp":"num","cb":"b193"},{"id":"visual.root.session.visual.emitter.groups[1422].2.displacement.x","lb":"x: 0.0","tp":"num","cb":"b193"},{"id":"visual.root.session.visual.emitter.groups[1422].2.displacement.y","lb":"y: 0.0","tp":"num","cb":"b193"},{"id":"visual.root.session.visual.emitter.groups[1422].2.displacement.z","lb":"z: 0.0","tp":"num","cb":"b193"}],"cb":"b193"},{"id":"visual.root.session.visual.emitter.groups[1422].2.link","lb":"link: 630","tp":"num","cb":"b193"},{"id":"visual.root.session.visual.emitter.groups[1422].2.scale","lb":"scale: 5.5","tp":"num","cb":"b193"},{"id":"visual.root.session.visual.emitter.groups[1422].2.toEmitter","lb":"toEmitter: true","tp":"bool","cb":"b193"}],"cb":"b193"},{"id":"visual.root.session.visual.emitter.groups[1422].3","lb":"3","tp":"obj","ch":[{"id":"visual.root.session.visual.emitter.groups[1422].3.displacement","lb":"displacement","tp":"obj","ch":[{"id":"visual.root.session.visual.emitter.groups[1422].3.displacement.length","lb":"length: 0.0","tp":"num","cb":"b193"},{"id":"visual.root.session.visual.emitter.groups[1422].3.displacement.x","lb":"x: 0.0","tp":"num","cb":"b193"},{"id":"visual.root.session.visual.emitter.groups[1422].3.displacement.y","lb":"y: 0.0","tp":"num","cb":"b193"},{"id":"visual.root.session.visual.emitter.groups[1422].3.displacement.z","lb":"z: 0.0","tp":"num","cb":"b193"}],"cb":"b193"},{"id":"visual.root.session.visual.emitter.groups[1422].3.link","lb":"link: 1755","tp":"num","cb":"b193"},{"id":"visual.root.session.visual.emitter.groups[1422].3.scale","lb":"scale: 1.0","tp":"num","cb":"b193"},{"id":"visual.root.session.visual.emitter.groups[1422].3.toEmitter","lb":"toEmitter: true","tp":"bool","cb":"b193"}],"cb":"b193"},{"id":"visual.root.session.visual.emitter.groups[1422].4","lb":"4","tp":"obj","ch":[{"id":"visual.root.session.visual.emitter.groups[1422].4.displacement","lb":"displacement","tp":"obj","ch":[{"id":"visual.root.session.visual.emitter.groups[1422].4.displacement.length","lb":"length: 0.0","tp":"num","cb":"b193"},{"id":"visual.root.session.visual.emitter.groups[1422].4.displacement.x","lb":"x: 0.0","tp":"num","cb":"b193"},{"id":"visual.root.session.visual.emitter.groups[1422].4.displacement.y","lb":"y: 0.0","tp":"num","cb":"b193"},{"id":"visual.root.session.visual.emitter.groups[1422].4.displacement.z","lb":"z: 0.0","tp":"num","cb":"b193"}],"cb":"b193"},{"id":"visual.root.session.visual.emitter.groups[1422].4.link","lb":"link: 450","tp":"num","cb":"b193"},{"id":"visual.root.session.visual.emitter.groups[1422].4.scale","lb":"scale: 1.0","tp":"num","cb":"b193"},{"id":"visual.root.session.visual.emitter.groups[1422].4.toEmitter","lb":"toEmitter: true","tp":"bool","cb":"b193"}],"cb":"b193"},{"id":"visual.root.session.visual.emitter.groups[1422].5","lb":"5","tp":"obj","ch":[{"id":"visual.root.session.visual.emitter.groups[1422].5.displacement","lb":"displacement","tp":"obj","ch":[{"id":"visual.root.session.visual.emitter.groups[1422].5.displacement.length","lb":"length: 0.0","tp":"num","cb":"b193"},{"id":"visual.root.session.visual.emitter.groups[1422].5.displacement.x","lb":"x: 0.0","tp":"num","cb":"b193"},{"id":"visual.root.session.visual.emitter.groups[1422].5.displacement.y","lb":"y: 0.0","tp":"num","cb":"b193"},{"id":"visual.root.session.visual.emitter.groups[1422].5.displacement.z","lb":"z: 0.0","tp":"num","cb":"b193"}],"cb":"b193"},{"id":"visual.root.session.visual.emitter.groups[1422].5.link","lb":"link: 449","tp":"num","cb":"b193"},{"id":"visual.root.session.visual.emitter.groups[1422].5.scale","lb":"scale: 1.0","tp":"num","cb":"b193"},{"id":"visual.root.session.visual.emitter.groups[1422].5.toEmitter","lb":"toEmitter: true","tp":"bool","cb":"b193"}],"cb":"b193"},{"id":"visual.root.session.visual.emitter.groups[1422].6","lb":"6","tp":"obj","ch":[{"id":"visual.root.session.visual.emitter.groups[1422].6.displacement","lb":"displacement","tp":"obj","ch":[{"id":"visual.root.session.visual.emitter.groups[1422].6.displacement.length","lb":"length: 0.0","tp":"num","cb":"b193"},{"id":"visual.root.session.visual.emitter.groups[1422].6.displacement.x","lb":"x: 0.0","tp":"num","cb":"b193"},{"id":"visual.root.session.visual.emitter.groups[1422].6.displacement.y","lb":"y: 0.0","tp":"num","cb":"b193"},{"id":"visual.root.session.visual.emitter.groups[1422].6.displacement.z","lb":"z: 0.0","tp":"num","cb":"b193"}],"cb":"b193"},{"id":"visual.root.session.visual.emitter.groups[1422].6.link","lb":"link: 443","tp":"num","cb":"b193"},{"id":"visual.root.session.visual.emitter.groups[1422].6.scale","lb":"scale: 1.0","tp":"num","cb":"b193"},{"id":"visual.root.session.visual.emitter.groups[1422].6.toEmitter","lb":"toEmitter: true","tp":"bool","cb":"b193"}],"cb":"b193"},{"id":"visual.root.session.visual.emitter.groups[1422].7","lb":"7","tp":"obj","ch":[{"id":"visual.root.session.visual.emitter.groups[1422].7.displacement","lb":"displacement","tp":"obj","ch":[{"id":"visual.root.session.visual.emitter.groups[1422].7.displacement.length","lb":"length: 0.0","tp":"num","cb":"b193"},{"id":"visual.root.session.visual.emitter.groups[1422].7.displacement.x","lb":"x: 0.0","tp":"num","cb":"b193"},{"id":"visual.root.session.visual.emitter.groups[1422].7.displacement.y","lb":"y: 0.0","tp":"num","cb":"b193"},{"id":"visual.root.session.visual.emitter.groups[1422].7.displacement.z","lb":"z: 0.0","tp":"num","cb":"b193"}],"cb":"b193"},{"id":"visual.root.session.visual.emitter.groups[1422].7.link","lb":"link: 446","tp":"num","cb":"b193"},{"id":"visual.root.session.visual.emitter.groups[1422].7.scale","lb":"scale: 1.0","tp":"num","cb":"b193"},{"id":"visual.root.session.visual.emitter.groups[1422].7.toEmitter","lb":"toEmitter: true","tp":"bool","cb":"b193"}],"cb":"b193"},{"id":"visual.root.session.visual.emitter.groups[1422].8","lb":"8","tp":"obj","ch":[{"id":"visual.root.session.visual.emitter.groups[1422].8.displacement","lb":"displacement","tp":"obj","ch":[{"id":"visual.root.session.visual.emitter.groups[1422].8.displacement.length","lb":"length: 0.0","tp":"num","cb":"b193"},{"id":"visual.root.session.visual.emitter.groups[1422].8.displacement.x","lb":"x: 0.0","tp":"num","cb":"b193"},{"id":"visual.root.session.visual.emitter.groups[1422].8.displacement.y","lb":"y: 0.0","tp":"num","cb":"b193"},{"id":"visual.root.session.visual.emitter.groups[1422].8.displacement.z","lb":"z: 0.0","tp":"num","cb":"b193"}],"cb":"b193"},{"id":"visual.root.session.visual.emitter.groups[1422].8.link","lb":"link: 444","tp":"num","cb":"b193"},{"id":"visual.root.session.visual.emitter.groups[1422].8.scale","lb":"scale: 1.0","tp":"num","cb":"b193"},{"id":"visual.root.session.visual.emitter.groups[1422].8.toEmitter","lb":"toEmitter: true","tp":"bool","cb":"b193"}],"cb":"b193"},{"id":"visual.root.session.visual.emitter.groups[1422].9","lb":"9","tp":"obj","ch":[{"id":"visual.root.session.visual.emitter.groups[1422].9.displacement","lb":"displacement","tp":"obj","ch":[{"id":"visual.root.session.visual.emitter.groups[1422].9.displacement.length","lb":"length: 0.0","tp":"num","cb":"b193"},{"id":"visual.root.session.visual.emitter.groups[1422].9.displacement.x","lb":"x: 0.0","tp":"num","cb":"b193"},{"id":"visual.root.session.visual.emitter.groups[1422].9.displacement.y","lb":"y: 0.0","tp":"num","cb":"b193"},{"id":"visual.root.session.visual.emitter.groups[1422].9.displacement.z","lb":"z: 0.0","tp":"num","cb":"b193"}],"cb":"b193"},{"id":"visual.root.session.visual.emitter.groups[1422].9.link","lb":"link: 445","tp":"num","cb":"b193"},{"id":"visual.root.session.visual.emitter.groups[1422].9.scale","lb":"scale: 1.0","tp":"num","cb":"b193"},{"id":"visual.root.session.visual.emitter.groups[1422].9.toEmitter","lb":"toEmitter: true","tp":"bool","cb":"b193"}],"cb":"b193"},{"id":"visual.root.session.visual.emitter.groups[1422].10","lb":"10","tp":"obj","ch":[{"id":"visual.root.session.visual.emitter.groups[1422].10.displacement","lb":"displacement","tp":"obj","ch":[{"id":"visual.root.session.visual.emitter.groups[1422].10.displacement.length","lb":"length: 0.0","tp":"num","cb":"b193"},{"id":"visual.root.session.visual.emitter.groups[1422].10.displacement.x","lb":"x: 0.0","tp":"num","cb":"b193"},{"id":"visual.root.session.visual.emitter.groups[1422].10.displacement.y","lb":"y: 0.0","tp":"num","cb":"b193"},{"id":"visual.root.session.visual.emitter.groups[1422].10.displacement.z","lb":"z: 0.0","tp":"num","cb":"b193"}],"cb":"b193"},{"id":"visual.root.session.visual.emitter.groups[1422].10.link","lb":"link: 447","tp":"num","cb":"b193"},{"id":"visual.root.session.visual.emitter.groups[1422].10.scale","lb":"scale: 1.0","tp":"num","cb":"b193"},{"id":"visual.root.session.visual.emitter.groups[1422].10.toEmitter","lb":"toEmitter: true","tp":"bool","cb":"b193"}],"cb":"b193"},{"id":"visual.root.session.visual.emitter.groups[1422].11","lb":"11","tp":"obj","ch":[{"id":"visual.root.session.visual.emitter.groups[1422].11.displacement","lb":"displacement","tp":"obj","ch":[{"id":"visual.root.session.visual.emitter.groups[1422].11.displacement.length","lb":"length: 0.0","tp":"num","cb":"b193"},{"id":"visual.root.session.visual.emitter.groups[1422].11.displacement.x","lb":"x: 0.0","tp":"num","cb":"b193"},{"id":"visual.root.session.visual.emitter.groups[1422].11.displacement.y","lb":"y: 0.0","tp":"num","cb":"b193"},{"id":"visual.root.session.visual.emitter.groups[1422].11.displacement.z","lb":"z: 0.0","tp":"num","cb":"b193"}],"cb":"b193"},{"id":"visual.root.session.visual.emitter.groups[1422].11.link","lb":"link: 448","tp":"num","cb":"b193"},{"id":"visual.root.session.visual.emitter.groups[1422].11.scale","lb":"scale: 1.0","tp":"num","cb":"b193"},{"id":"visual.root.session.visual.emitter.groups[1422].11.toEmitter","lb":"toEmitter: true","tp":"bool","cb":"b193"}],"cb":"b193"},{"id":"visual.root.session.visual.emitter.groups[1422].12","lb":"12","tp":"obj","ch":[{"id":"visual.root.session.visual.emitter.groups[1422].12.displacement","lb":"displacement","tp":"obj","ch":[{"id":"visual.root.session.visual.emitter.groups[1422].12.displacement.length","lb":"length: 0.0","tp":"num","cb":"b193"},{"id":"visual.root.session.visual.emitter.groups[1422].12.displacement.x","lb":"x: 0.0","tp":"num","cb":"b193"},{"id":"visual.root.session.visual.emitter.groups[1422].12.displacement.y","lb":"y: 0.0","tp":"num","cb":"b193"},{"id":"visual.root.session.visual.emitter.groups[1422].12.displacement.z","lb":"z: 0.0","tp":"num","cb":"b193"}],"cb":"b193"},{"id":"visual.root.session.visual.emitter.groups[1422].12.link","lb":"link: 425","tp":"num","cb":"b193"},{"id":"visual.root.session.visual.emitter.groups[1422].12.scale","lb":"scale: 1.0","tp":"num","cb":"b193"},{"id":"visual.root.session.visual.emitter.groups[1422].12.toEmitter","lb":"toEmitter: true","tp":"bool","cb":"b193"}],"cb":"b193"},{"id":"visual.root.session.visual.emitter.groups[1422].13","lb":"13","tp":"obj","ch":[{"id":"visual.root.session.visual.emitter.groups[1422].13.displacement","lb":"displacement","tp":"obj","ch":[{"id":"visual.root.session.visual.emitter.groups[1422].13.displacement.length","lb":"length: 0.0","tp":"num","cb":"b193"},{"id":"visual.root.session.visual.emitter.groups[1422].13.displacement.x","lb":"x: 0.0","tp":"num","cb":"b193"},{"id":"visual.root.session.visual.emitter.groups[1422].13.displacement.y","lb":"y: 0.0","tp":"num","cb":"b193"},{"id":"visual.root.session.visual.emitter.groups[1422].13.displacement.z","lb":"z: 0.0","tp":"num","cb":"b193"}],"cb":"b193"},{"id":"visual.root.session.visual.emitter.groups[1422].13.link","lb":"link: 426","tp":"num","cb":"b193"},{"id":"visual.root.session.visual.emitter.groups[1422].13.scale","lb":"scale: 1.0","tp":"num","cb":"b193"},{"id":"visual.root.session.visual.emitter.groups[1422].13.toEmitter","lb":"toEmitter: true","tp":"bool","cb":"b193"}],"cb":"b193"},{"id":"visual.root.session.visual.emitter.groups[1422].14","lb":"14","tp":"obj","ch":[{"id":"visual.root.session.visual.emitter.groups[1422].14.displacement","lb":"displacement","tp":"obj","ch":[{"id":"visual.root.session.visual.emitter.groups[1422].14.displacement.length","lb":"length: 0.0","tp":"num","cb":"b193"},{"id":"visual.root.session.visual.emitter.groups[1422].14.displacement.x","lb":"x: 0.0","tp":"num","cb":"b193"},{"id":"visual.root.session.visual.emitter.groups[1422].14.displacement.y","lb":"y: 0.0","tp":"num","cb":"b193"},{"id":"visual.root.session.visual.emitter.groups[1422].14.displacement.z","lb":"z: 0.0","tp":"num","cb":"b193"}],"cb":"b193"},{"id":"visual.root.session.visual.emitter.groups[1422].14.link","lb":"link: 427","tp":"num","cb":"b193"},{"id":"visual.root.session.visual.emitter.groups[1422].14.scale","lb":"scale: 1.0","tp":"num","cb":"b193"},{"id":"visual.root.session.visual.emitter.groups[1422].14.toEmitter","lb":"toEmitter: true","tp":"bool","cb":"b193"}],"cb":"b193"},{"id":"visual.root.session.visual.emitter.groups[1422].15","lb":"15","tp":"obj","ch":[{"id":"visual.root.session.visual.emitter.groups[1422].15.displacement","lb":"displacement","tp":"obj","ch":[{"id":"visual.root.session.visual.emitter.groups[1422].15.displacement.length","lb":"length: 0.0","tp":"num","cb":"b193"},{"id":"visual.root.session.visual.emitter.groups[1422].15.displacement.x","lb":"x: 0.0","tp":"num","cb":"b193"},{"id":"visual.root.session.visual.emitter.groups[1422].15.displacement.y","lb":"y: 0.0","tp":"num","cb":"b193"},{"id":"visual.root.session.visual.emitter.groups[1422].15.displacement.z","lb":"z: 0.0","tp":"num","cb":"b193"}],"cb":"b193"},{"id":"visual.root.session.visual.emitter.groups[1422].15.link","lb":"link: 428","tp":"num","cb":"b193"},{"id":"visual.root.session.visual.emitter.groups[1422].15.scale","lb":"scale: 1.0","tp":"num","cb":"b193"},{"id":"visual.root.session.visual.emitter.groups[1422].15.toEmitter","lb":"toEmitter: true","tp":"bool","cb":"b193"}],"cb":"b193"},{"id":"visual.root.session.visual.emitter.groups[1422].16","lb":"16","tp":"obj","ch":[{"id":"visual.root.session.visual.emitter.groups[1422].16.displacement","lb":"displacement","tp":"obj","ch":[{"id":"visual.root.session.visual.emitter.groups[1422].16.displacement.length","lb":"length: 0.0","tp":"num","cb":"b193"},{"id":"visual.root.session.visual.emitter.groups[1422].16.displacement.x","lb":"x: 0.0","tp":"num","cb":"b193"},{"id":"visual.root.session.visual.emitter.groups[1422].16.displacement.y","lb":"y: 0.0","tp":"num","cb":"b193"},{"id":"visual.root.session.visual.emitter.groups[1422].16.displacement.z","lb":"z: 0.0","tp":"num","cb":"b193"}],"cb":"b193"},{"id":"visual.root.session.visual.emitter.groups[1422].16.link","lb":"link: 429","tp":"num","cb":"b193"},{"id":"visual.root.session.visual.emitter.groups[1422].16.scale","lb":"scale: 1.0","tp":"num","cb":"b193"},{"id":"visual.root.session.visual.emitter.groups[1422].16.toEmitter","lb":"toEmitter: true","tp":"bool","cb":"b193"}],"cb":"b193"},{"id":"visual.root.session.visual.emitter.groups[1422].17","lb":"17","tp":"obj","ch":[{"id":"visual.root.session.visual.emitter.groups[1422].17.displacement","lb":"displacement","tp":"obj","ch":[{"id":"visual.root.session.visual.emitter.groups[1422].17.displacement.length","lb":"length: 0.0","tp":"num","cb":"b193"},{"id":"visual.root.session.visual.emitter.groups[1422].17.displacement.x","lb":"x: 0.0","tp":"num","cb":"b193"},{"id":"visual.root.session.visual.emitter.groups[1422].17.displacement.y","lb":"y: 0.0","tp":"num","cb":"b193"},{"id":"visual.root.session.visual.emitter.groups[1422].17.displacement.z","lb":"z: 0.0","tp":"num","cb":"b193"}],"cb":"b193"},{"id":"visual.root.session.visual.emitter.groups[1422].17.link","lb":"link: 430","tp":"num","cb":"b193"},{"id":"visual.root.session.visual.emitter.groups[1422].17.scale","lb":"scale: 1.0","tp":"num","cb":"b193"},{"id":"visual.root.session.visual.emitter.groups[1422].17.toEmitter","lb":"toEmitter: true","tp":"bool","cb":"b193"}],"cb":"b193"},{"id":"visual.root.session.visual.emitter.groups[1422].18","lb":"18","tp":"obj","ch":[{"id":"visual.root.session.visual.emitter.groups[1422].18.displacement","lb":"displacement","tp":"obj","ch":[{"id":"visual.root.session.visual.emitter.groups[1422].18.displacement.length","lb":"length: 0.0","tp":"num","cb":"b193"},{"id":"visual.root.session.visual.emitter.groups[1422].18.displacement.x","lb":"x: 0.0","tp":"num","cb":"b193"},{"id":"visual.root.session.visual.emitter.groups[1422].18.displacement.y","lb":"y: 0.0","tp":"num","cb":"b193"},{"id":"visual.root.session.visual.emitter.groups[1422].18.displacement.z","lb":"z: 0.0","tp":"num","cb":"b193"}],"cb":"b193"},{"id":"visual.root.session.visual.emitter.groups[1422].18.link","lb":"link: 431","tp":"num","cb":"b193"},{"id":"visual.root.session.visual.emitter.groups[1422].18.scale","lb":"scale: 1.0","tp":"num","cb":"b193"},{"id":"visual.root.session.visual.emitter.groups[1422].18.toEmitter","lb":"toEmitter: true","tp":"bool","cb":"b193"}],"cb":"b193"},{"id":"visual.root.session.visual.emitter.groups[1422].19","lb":"19","tp":"obj","ch":[{"id":"visual.root.session.visual.emitter.groups[1422].19.displacement","lb":"displacement","tp":"obj","ch":[{"id":"visual.root.session.visual.emitter.groups[1422].19.displacement.length","lb":"length: 0.0","tp":"num","cb":"b193"},{"id":"visual.root.session.visual.emitter.groups[1422].19.displacement.x","lb":"x: 0.0","tp":"num","cb":"b193"},{"id":"visual.root.session.visual.emitter.groups[1422].19.displacement.y","lb":"y: 0.0","tp":"num","cb":"b193"},{"id":"visual.root.session.visual.emitter.groups[1422].19.displacement.z","lb":"z: 0.0","tp":"num","cb":"b193"}],"cb":"b193"},{"id":"visual.root.session.visual.emitter.groups[1422].19.link","lb":"link: 432","tp":"num","cb":"b193"},{"id":"visual.root.session.visual.emitter.groups[1422].19.scale","lb":"scale: 1.0","tp":"num","cb":"b193"},{"id":"visual.root.session.visual.emitter.groups[1422].19.toEmitter","lb":"toEmitter: true","tp":"bool","cb":"b193"}],"cb":"b193"},{"id":"visual.root.session.visual.emitter.groups[1422].20","lb":"20","tp":"obj","ch":[{"id":"visual.root.session.visual.emitter.groups[1422].20.displacement","lb":"displacement","tp":"obj","ch":[{"id":"visual.root.session.visual.emitter.groups[1422].20.displacement.length","lb":"length: 0.0","tp":"num","cb":"b193"},{"id":"visual.root.session.visual.emitter.groups[1422].20.displacement.x","lb":"x: 0.0","tp":"num","cb":"b193"},{"id":"visual.root.session.visual.emitter.groups[1422].20.displacement.y","lb":"y: 0.0","tp":"num","cb":"b193"},{"id":"visual.root.session.visual.emitter.groups[1422].20.displacement.z","lb":"z: 0.0","tp":"num","cb":"b193"}],"cb":"b193"},{"id":"visual.root.session.visual.emitter.groups[1422].20.link","lb":"link: 433","tp":"num","cb":"b193"},{"id":"visual.root.session.visual.emitter.groups[1422].20.scale","lb":"scale: 1.0","tp":"num","cb":"b193"},{"id":"visual.root.session.visual.emitter.groups[1422].20.toEmitter","lb":"toEmitter: true","tp":"bool","cb":"b193"}],"cb":"b193"},{"id":"visual.root.session.visual.emitter.groups[1422].21","lb":"21","tp":"obj","ch":[{"id":"visual.root.session.visual.emitter.groups[1422].21.displacement","lb":"displacement","tp":"obj","ch":[{"id":"visual.root.session.visual.emitter.groups[1422].21.displacement.length","lb":"length: 0.0","tp":"num","cb":"b193"},{"id":"visual.root.session.visual.emitter.groups[1422].21.displacement.x","lb":"x: 0.0","tp":"num","cb":"b193"},{"id":"visual.root.session.visual.emitter.groups[1422].21.displacement.y","lb":"y: 0.0","tp":"num","cb":"b193"},{"id":"visual.root.session.visual.emitter.groups[1422].21.displacement.z","lb":"z: 0.0","tp":"num","cb":"b193"}],"cb":"b193"},{"id":"visual.root.session.visual.emitter.groups[1422].21.link","lb":"link: 434","tp":"num","cb":"b193"},{"id":"visual.root.session.visual.emitter.groups[1422].21.scale","lb":"scale: 1.0","tp":"num","cb":"b193"},{"id":"visual.root.session.visual.emitter.groups[1422].21.toEmitter","lb":"toEmitter: true","tp":"bool","cb":"b193"}],"cb":"b193"},{"id":"visual.root.session.visual.emitter.groups[1422].22","lb":"22","tp":"obj","ch":[{"id":"visual.root.session.visual.emitter.groups[1422].22.displacement","lb":"displacement","tp":"obj","ch":[{"id":"visual.root.session.visual.emitter.groups[1422].22.displacement.length","lb":"length: 0.0","tp":"num","cb":"b193"},{"id":"visual.root.session.visual.emitter.groups[1422].22.displacement.x","lb":"x: 0.0","tp":"num","cb":"b193"},{"id":"visual.root.session.visual.emitter.groups[1422].22.displacement.y","lb":"y: 0.0","tp":"num","cb":"b193"},{"id":"visual.root.session.visual.emitter.groups[1422].22.displacement.z","lb":"z: 0.0","tp":"num","cb":"b193"}],"cb":"b193"},{"id":"visual.root.session.visual.emitter.groups[1422].22.link","lb":"link: 435","tp":"num","cb":"b193"},{"id":"visual.root.session.visual.emitter.groups[1422].22.scale","lb":"scale: 1.0","tp":"num","cb":"b193"},{"id":"visual.root.session.visual.emitter.groups[1422].22.toEmitter","lb":"toEmitter: true","tp":"bool","cb":"b193"}],"cb":"b193"},{"id":"visual.root.session.visual.emitter.groups[1422].23","lb":"23","tp":"obj","ch":[{"id":"visual.root.session.visual.emitter.groups[1422].23.displacement","lb":"displacement","tp":"obj","ch":[{"id":"visual.root.session.visual.emitter.groups[1422].23.displacement.length","lb":"length: 0.0","tp":"num","cb":"b193"},{"id":"visual.root.session.visual.emitter.groups[1422].23.displacement.x","lb":"x: 0.0","tp":"num","cb":"b193"},{"id":"visual.root.session.visual.emitter.groups[1422].23.displacement.y","lb":"y: 0.0","tp":"num","cb":"b193"},{"id":"visual.root.session.visual.emitter.groups[1422].23.displacement.z","lb":"z: 0.0","tp":"num","cb":"b193"}],"cb":"b193"},{"id":"visual.root.session.visual.emitter.groups[1422].23.link","lb":"link: 436","tp":"num","cb":"b193"},{"id":"visual.root.session.visual.emitter.groups[1422].23.scale","lb":"scale: 1.0","tp":"num","cb":"b193"},{"id":"visual.root.session.visual.emitter.groups[1422].23.toEmitter","lb":"toEmitter: true","tp":"bool","cb":"b193"}],"cb":"b193"},{"id":"visual.root.session.visual.emitter.groups[1422].24","lb":"24","tp":"obj","ch":[{"id":"visual.root.session.visual.emitter.groups[1422].24.displacement","lb":"displacement","tp":"obj","ch":[{"id":"visual.root.session.visual.emitter.groups[1422].24.displacement.length","lb":"length: 0.0","tp":"num","cb":"b193"},{"id":"visual.root.session.visual.emitter.groups[1422].24.displacement.x","lb":"x: 0.0","tp":"num","cb":"b193"},{"id":"visual.root.session.visual.emitter.groups[1422].24.displacement.y","lb":"y: 0.0","tp":"num","cb":"b193"},{"id":"visual.root.session.visual.emitter.groups[1422].24.displacement.z","lb":"z: 0.0","tp":"num","cb":"b193"}],"cb":"b193"},{"id":"visual.root.session.visual.emitter.groups[1422].24.link","lb":"link: 437","tp":"num","cb":"b193"},{"id":"visual.root.session.visual.emitter.groups[1422].24.scale","lb":"scale: 1.0","tp":"num","cb":"b193"},{"id":"visual.root.session.visual.emitter.groups[1422].24.toEmitter","lb":"toEmitter: true","tp":"bool","cb":"b193"}],"cb":"b193"},{"id":"visual.root.session.visual.emitter.groups[1422].25","lb":"25","tp":"obj","ch":[{"id":"visual.root.session.visual.emitter.groups[1422].25.displacement","lb":"displacement","tp":"obj","ch":[{"id":"visual.root.session.visual.emitter.groups[1422].25.displacement.length","lb":"length: 0.0","tp":"num","cb":"b193"},{"id":"visual.root.session.visual.emitter.groups[1422].25.displacement.x","lb":"x: 0.0","tp":"num","cb":"b193"},{"id":"visual.root.session.visual.emitter.groups[1422].25.displacement.y","lb":"y: 0.0","tp":"num","cb":"b193"},{"id":"visual.root.session.visual.emitter.groups[1422].25.displacement.z","lb":"z: 0.0","tp":"num","cb":"b193"}],"cb":"b193"},{"id":"visual.root.session.visual.emitter.groups[1422].25.link","lb":"link: 438","tp":"num","cb":"b193"},{"id":"visual.root.session.visual.emitter.groups[1422].25.scale","lb":"scale: 1.0","tp":"num","cb":"b193"},{"id":"visual.root.session.visual.emitter.groups[1422].25.toEmitter","lb":"toEmitter: true","tp":"bool","cb":"b193"}],"cb":"b193"},{"id":"visual.root.session.visual.emitter.groups[1422].26","lb":"26","tp":"obj","ch":[{"id":"visual.root.session.visual.emitter.groups[1422].26.displacement","lb":"displacement","tp":"obj","ch":[{"id":"visual.root.session.visual.emitter.groups[1422].26.displacement.length","lb":"length: 0.0","tp":"num","cb":"b193"},{"id":"visual.root.session.visual.emitter.groups[1422].26.displacement.x","lb":"x: 0.0","tp":"num","cb":"b193"},{"id":"visual.root.session.visual.emitter.groups[1422].26.displacement.y","lb":"y: 0.0","tp":"num","cb":"b193"},{"id":"visual.root.session.visual.emitter.groups[1422].26.displacement.z","lb":"z: 0.0","tp":"num","cb":"b193"}],"cb":"b193"},{"id":"visual.root.session.visual.emitter.groups[1422].26.link","lb":"link: 439","tp":"num","cb":"b193"},{"id":"visual.root.session.visual.emitter.groups[1422].26.scale","lb":"scale: 1.0","tp":"num","cb":"b193"},{"id":"visual.root.session.visual.emitter.groups[1422].26.toEmitter","lb":"toEmitter: true","tp":"bool","cb":"b193"}],"cb":"b193"},{"id":"visual.root.session.visual.emitter.groups[1422].27","lb":"27","tp":"obj","ch":[{"id":"visual.root.session.visual.emitter.groups[1422].27.displacement","lb":"displacement","tp":"obj","ch":[{"id":"visual.root.session.visual.emitter.groups[1422].27.displacement.length","lb":"length: 0.0","tp":"num","cb":"b193"},{"id":"visual.root.session.visual.emitter.groups[1422].27.displacement.x","lb":"x: 0.0","tp":"num","cb":"b193"},{"id":"visual.root.session.visual.emitter.groups[1422].27.displacement.y","lb":"y: 0.0","tp":"num","cb":"b193"},{"id":"visual.root.session.visual.emitter.groups[1422].27.displacement.z","lb":"z: 0.0","tp":"num","cb":"b193"}],"cb":"b193"},{"id":"visual.root.session.visual.emitter.groups[1422].27.link","lb":"link: 430","tp":"num","cb":"b193"},{"id":"visual.root.session.visual.emitter.groups[1422].27.scale","lb":"scale: 1.0","tp":"num","cb":"b193"},{"id":"visual.root.session.visual.emitter.groups[1422].27.toEmitter","lb":"toEmitter: true","tp":"bool","cb":"b193"}],"cb":"b193"},{"id":"visual.root.session.visual.emitter.groups[1422].28","lb":"28","tp":"obj","ch":[{"id":"visual.root.session.visual.emitter.groups[1422].28.displacement","lb":"displacement","tp":"obj","ch":[{"id":"visual.root.session.visual.emitter.groups[1422].28.displacement.length","lb":"length: 0.0","tp":"num","cb":"b193"},{"id":"visual.root.session.visual.emitter.groups[1422].28.displacement.x","lb":"x: 0.0","tp":"num","cb":"b193"},{"id":"visual.root.session.visual.emitter.groups[1422].28.displacement.y","lb":"y: 0.0","tp":"num","cb":"b193"},{"id":"visual.root.session.visual.emitter.groups[1422].28.displacement.z","lb":"z: 0.0","tp":"num","cb":"b193"}],"cb":"b193"},{"id":"visual.root.session.visual.emitter.groups[1422].28.link","lb":"link: 441","tp":"num","cb":"b193"},{"id":"visual.root.session.visual.emitter.groups[1422].28.scale","lb":"scale: 1.0","tp":"num","cb":"b193"},{"id":"visual.root.session.visual.emitter.groups[1422].28.toEmitter","lb":"toEmitter: true","tp":"bool","cb":"b193"}],"cb":"b193"},{"id":"visual.root.session.visual.emitter.groups[1422].29","lb":"29","tp":"obj","ch":[{"id":"visual.root.session.visual.emitter.groups[1422].29.displacement","lb":"displacement","tp":"obj","ch":[{"id":"visual.root.session.visual.emitter.groups[1422].29.displacement.length","lb":"length: 0.0","tp":"num","cb":"b193"},{"id":"visual.root.session.visual.emitter.groups[1422].29.displacement.x","lb":"x: 0.0","tp":"num","cb":"b193"},{"id":"visual.root.session.visual.emitter.groups[1422].29.displacement.y","lb":"y: 0.0","tp":"num","cb":"b193"},{"id":"visual.root.session.visual.emitter.groups[1422].29.displacement.z","lb":"z: 0.0","tp":"num","cb":"b193"}],"cb":"b193"},{"id":"visual.root.session.visual.emitter.groups[1422].29.link","lb":"link: 442","tp":"num","cb":"b193"},{"id":"visual.root.session.visual.emitter.groups[1422].29.scale","lb":"scale: 1.0","tp":"num","cb":"b193"},{"id":"visual.root.session.visual.emitter.groups[1422].29.toEmitter","lb":"toEmitter: true","tp":"bool","cb":"b193"}],"cb":"b193"},{"id":"visual.root.session.visual.emitter.groups[1422].30","lb":"30","tp":"obj","ch":[{"id":"visual.root.session.visual.emitter.groups[1422].30.displacement","lb":"displacement","tp":"obj","ch":[{"id":"visual.root.session.visual.emitter.groups[1422].30.displacement.length","lb":"length: 0.0","tp":"num","cb":"b193"},{"id":"visual.root.session.visual.emitter.groups[1422].30.displacement.x","lb":"x: 0.0","tp":"num","cb":"b193"},{"id":"visual.root.session.visual.emitter.groups[1422].30.displacement.y","lb":"y: 0.0","tp":"num","cb":"b193"},{"id":"visual.root.session.visual.emitter.groups[1422].30.displacement.z","lb":"z: 0.0","tp":"num","cb":"b193"}],"cb":"b193"},{"id":"visual.root.session.visual.emitter.groups[1422].30.link","lb":"link: 2479","tp":"num","cb":"b193"},{"id":"visual.root.session.visual.emitter.groups[1422].30.scale","lb":"scale: 2.5","tp":"num","cb":"b193"},{"id":"visual.root.session.visual.emitter.groups[1422].30.toEmitter","lb":"toEmitter: false","tp":"bool","cb":"b193"}],"cb":"b193"},{"id":"visual.root.session.visual.emitter.groups[1422].31","lb":"31","tp":"obj","ch":[{"id":"visual.root.session.visual.emitter.groups[1422].31.displacement","lb":"displacement","tp":"obj","ch":[{"id":"visual.root.session.visual.emitter.groups[1422].31.displacement.length","lb":"length: 0.0","tp":"num","cb":"b193"},{"id":"visual.root.session.visual.emitter.groups[1422].31.displacement.x","lb":"x: 0.0","tp":"num","cb":"b193"},{"id":"visual.root.session.visual.emitter.groups[1422].31.displacement.y","lb":"y: 0.0","tp":"num","cb":"b193"},{"id":"visual.root.session.visual.emitter.groups[1422].31.displacement.z","lb":"z: 0.0","tp":"num","cb":"b193"}],"cb":"b193"},{"id":"visual.root.session.visual.emitter.groups[1422].31.link","lb":"link: 2476","tp":"num","cb":"b193"},{"id":"visual.root.session.visual.emitter.groups[1422].31.scale","lb":"scale: 1.399999976158142","tp":"num","cb":"b193"},{"id":"visual.root.session.visual.emitter.groups[1422].31.toEmitter","lb":"toEmitter: false","tp":"bool","cb":"b193"}],"cb":"b193"},{"id":"visual.root.session.visual.emitter.groups[1422].32","lb":"32","tp":"obj","ch":[{"id":"visual.root.session.visual.emitter.groups[1422].32.displacement","lb":"displacement","tp":"obj","ch":[{"id":"visual.root.session.visual.emitter.groups[1422].32.displacement.length","lb":"length: 45.0","tp":"num","cb":"b193"},{"id":"visual.root.session.visual.emitter.groups[1422].32.displacement.x","lb":"x: -45.0","tp":"num","cb":"b193"},{"id":"visual.root.session.visual.emitter.groups[1422].32.displacement.y","lb":"y: 0.0","tp":"num","cb":"b193"},{"id":"visual.root.session.visual.emitter.groups[1422].32.displacement.z","lb":"z: 0.0","tp":"num","cb":"b193"}],"cb":"b193"},{"id":"visual.root.session.visual.emitter.groups[1422].32.link","lb":"link: 2480","tp":"num","cb":"b193"},{"id":"visual.root.session.visual.emitter.groups[1422].32.scale","lb":"scale: 1.2000000476837158","tp":"num","cb":"b193"},{"id":"visual.root.session.visual.emitter.groups[1422].32.toEmitter","lb":"toEmitter: false","tp":"bool","cb":"b193"}],"cb":"b193"},{"id":"visual.root.session.visual.emitter.groups[1422].33","lb":"33","tp":"obj","ch":[{"id":"visual.root.session.visual.emitter.groups[1422].33.displacement","lb":"displacement","tp":"obj","ch":[{"id":"visual.root.session.visual.emitter.groups[1422].33.displacement.length","lb":"length: 45.0","tp":"num","cb":"b193"},{"id":"visual.root.session.visual.emitter.groups[1422].33.displacement.x","lb":"x: 45.0","tp":"num","cb":"b193"},{"id":"visual.root.session.visual.emitter.groups[1422].33.displacement.y","lb":"y: 0.0","tp":"num","cb":"b193"},{"id":"visual.root.session.visual.emitter.groups[1422].33.displacement.z","lb":"z: 0.0","tp":"num","cb":"b193"}],"cb":"b193"},{"id":"visual.root.session.visual.emitter.groups[1422].33.link","lb":"link: 2480","tp":"num","cb":"b193"},{"id":"visual.root.session.visual.emitter.groups[1422].33.scale","lb":"scale: 1.2000000476837158","tp":"num","cb":"b193"},{"id":"visual.root.session.visual.emitter.groups[1422].33.toEmitter","lb":"toEmitter: false","tp":"bool","cb":"b193"}],"cb":"b193"},{"id":"visual.root.session.visual.emitter.groups[1422].34","lb":"34","tp":"obj","ch":[{"id":"visual.root.session.visual.emitter.groups[1422].34.displacement","lb":"displacement","tp":"obj","ch":[{"id":"visual.root.session.visual.emitter.groups[1422].34.displacement.length","lb":"length: 0.0","tp":"num","cb":"b193"},{"id":"visual.root.session.visual.emitter.groups[1422].34.displacement.x","lb":"x: 0.0","tp":"num","cb":"b193"},{"id":"visual.root.session.visual.emitter.groups[1422].34.displacement.y","lb":"y: 0.0","tp":"num","cb":"b193"},{"id":"visual.root.session.visual.emitter.groups[1422].34.displacement.z","lb":"z: 0.0","tp":"num","cb":"b193"}],"cb":"b193"},{"id":"visual.root.session.visual.emitter.groups[1422].34.link","lb":"link: 1778","tp":"num","cb":"b193"},{"id":"visual.root.session.visual.emitter.groups[1422].34.scale","lb":"scale: 1.0","tp":"num","cb":"b193"},{"id":"visual.root.session.visual.emitter.groups[1422].34.toEmitter","lb":"toEmitter: true","tp":"bool","cb":"b193"}],"cb":"b193"},{"id":"visual.root.session.visual.emitter.groups[1422].35","lb":"35","tp":"obj","ch":[{"id":"visual.root.session.visual.emitter.groups[1422].35.displacement","lb":"displacement","tp":"obj","ch":[{"id":"visual.root.session.visual.emitter.groups[1422].35.displacement.length","lb":"length: 0.0","tp":"num","cb":"b193"},{"id":"visual.root.session.visual.emitter.groups[1422].35.displacement.x","lb":"x: 0.0","tp":"num","cb":"b193"},{"id":"visual.root.session.visual.emitter.groups[1422].35.displacement.y","lb":"y: 0.0","tp":"num","cb":"b193"},{"id":"visual.root.session.visual.emitter.groups[1422].35.displacement.z","lb":"z: 0.0","tp":"num","cb":"b193"}],"cb":"b193"},{"id":"visual.root.session.visual.emitter.groups[1422].35.link","lb":"link: 1779","tp":"num","cb":"b193"},{"id":"visual.root.session.visual.emitter.groups[1422].35.scale","lb":"scale: 1.0","tp":"num","cb":"b193"},{"id":"visual.root.session.visual.emitter.groups[1422].35.toEmitter","lb":"toEmitter: true","tp":"bool","cb":"b193"}],"cb":"b193"},{"id":"visual.root.session.visual.emitter.groups[1422].36","lb":"36","tp":"obj","ch":[{"id":"visual.root.session.visual.emitter.groups[1422].36.displacement","lb":"displacement","tp":"obj","ch":[{"id":"visual.root.session.visual.emitter.groups[1422].36.displacement.length","lb":"length: 122.06555938720703","tp":"num","cb":"b193"},{"id":"visual.root.session.visual.emitter.groups[1422].36.displacement.x","lb":"x: -60.0","tp":"num","cb":"b193"},{"id":"visual.root.session.visual.emitter.groups[1422].36.displacement.y","lb":"y: -80.0","tp":"num","cb":"b193"},{"id":"visual.root.session.visual.emitter.groups[1422].36.displacement.z","lb":"z: 70.0","tp":"num","cb":"b193"}],"cb":"b193"},{"id":"visual.root.session.visual.emitter.groups[1422].36.link","lb":"link: 1798","tp":"num","cb":"b193"},{"id":"visual.root.session.visual.emitter.groups[1422].36.scale","lb":"scale: 1.0","tp":"num","cb":"b193"},{"id":"visual.root.session.visual.emitter.groups[1422].36.toEmitter","lb":"toEmitter: true","tp":"bool","cb":"b193"}],"cb":"b193"},{"id":"visual.root.session.visual.emitter.groups[1422].37","lb":"37","tp":"obj","ch":[{"id":"visual.root.session.visual.emitter.groups[1422].37.displacement","lb":"displacement","tp":"obj","ch":[{"id":"visual.root.session.visual.emitter.groups[1422].37.displacement.length","lb":"length: 0.0","tp":"num","cb":"b193"},{"id":"visual.root.session.visual.emitter.groups[1422].37.displacement.x","lb":"x: 0.0","tp":"num","cb":"b193"},{"id":"visual.root.session.visual.emitter.groups[1422].37.displacement.y","lb":"y: 0.0","tp":"num","cb":"b193"},{"id":"visual.root.session.visual.emitter.groups[1422].37.displacement.z","lb":"z: 0.0","tp":"num","cb":"b193"}],"cb":"b193"},{"id":"visual.root.session.visual.emitter.groups[1422].37.link","lb":"link: 1800","tp":"num","cb":"b193"},{"id":"visual.root.session.visual.emitter.groups[1422].37.scale","lb":"scale: 1.0","tp":"num","cb":"b193"},{"id":"visual.root.session.visual.emitter.groups[1422].37.toEmitter","lb":"toEmitter: true","tp":"bool","cb":"b193"}],"cb":"b193"}]