[{"id":"visual.root.session.visual.content.model[1726].albedo","lb":"albedo: 2779","tp":"num","cb":"b118"},{"id":"visual.root.session.visual.content.model[1726].cullTargets","lb":"cullTargets: 0","tp":"num","cb":"b118"},{"id":"visual.root.session.visual.content.model[1726].emission","lb":"emission: 1.0","tp":"num","cb":"b118"},{"id":"visual.root.session.visual.content.model[1726].material","lb":"material: 2780","tp":"num","cb":"b118"},{"id":"visual.root.session.visual.content.model[1726].points","lb":"points","tp":"obj","ch":[{"id":"visual.root.session.visual.content.model[1726].points.f_clear","lb":"f_clear()","tp":"func","cb":"b118"},{"id":"visual.root.session.visual.content.model[1726].points.f_copy","lb":"f_copy(fromId, toId)","tp":"func","cb":"b118"},{"id":"visual.root.session.visual.content.model[1726].points.f_create","lb":"f_create()","tp":"func","cb":"b118"},{"id":"visual.root.session.visual.content.model[1726].points.f_insert","lb":"f_insert(index)","tp":"func","cb":"b118"},{"id":"visual.root.session.visual.content.model[1726].points.f_move","lb":"f_move(fromIndex, toIndex)","tp":"func","cb":"b118"},{"id":"visual.root.session.visual.content.model[1726].points.f_remove","lb":"f_remove(index)","tp":"func","cb":"b118"},{"id":"visual.root.session.visual.content.model[1726].points.size","lb":"size: 3","tp":"num","cb":"b118"},{"id":"visual.root.session.visual.content.model[1726].points[0]","lb":"0","tp":"obj","ch":[{"id":"visual.root.session.visual.content.model[1726].points[0].bone","lb":"bone: 11","tp":"num","cb":"b118"},{"id":"visual.root.session.visual.content.model[1726].points[0].offset","lb":"offset","tp":"obj","ch":[{"id":"visual.root.session.visual.content.model[1726].points[0].offset.x","lb":"x: 0.0","tp":"num","cb":"b118"},{"id":"visual.root.session.visual.content.model[1726].points[0].offset.y","lb":"y: 0.0","tp":"num","cb":"b118"},{"id":"visual.root.session.visual.content.model[1726].points[0].offset.z","lb":"z: 0.0","tp":"num","cb":"b118"}],"cb":"b118"}],"cb":"b118"},{"id":"visual.root.session.visual.content.model[1726].points[1]","lb":"1","tp":"obj","ch":[{"id":"visual.root.session.visual.content.model[1726].points[1].bone","lb":"bone: 12","tp":"num","cb":"b118"},{"id":"visual.root.session.visual.content.model[1726].points[1].offset","lb":"offset","tp":"obj","ch":[{"id":"visual.root.session.visual.content.model[1726].points[1].offset.x","lb":"x: 0.0","tp":"num","cb":"b118"},{"id":"visual.root.session.visual.content.model[1726].points[1].offset.y","lb":"y: 0.0","tp":"num","cb":"b118"},{"id":"visual.root.session.visual.content.model[1726].points[1].offset.z","lb":"z: 0.0","tp":"num","cb":"b118"}],"cb":"b118"}],"cb":"b118"},{"id":"visual.root.session.visual.content.model[1726].points[2]","lb":"2","tp":"obj","ch":[{"id":"visual.root.session.visual.content.model[1726].points[2].bone","lb":"bone: 13","tp":"num","cb":"b118"},{"id":"visual.root.session.visual.content.model[1726].points[2].offset","lb":"offset","tp":"obj","ch":[{"id":"visual.root.session.visual.content.model[1726].points[2].offset.x","lb":"x: 0.0","tp":"num","cb":"b118"},{"id":"visual.root.session.visual.content.model[1726].points[2].offset.y","lb":"y: 0.0","tp":"num","cb":"b118"},{"id":"visual.root.session.visual.content.model[1726].points[2].offset.z","lb":"z: 0.0","tp":"num","cb":"b118"}],"cb":"b118"}],"cb":"b118"}],"cb":"b118"},{"id":"visual.root.session.visual.content.model[1726].specular","lb":"specular: 1.0","tp":"num","cb":"b118"},{"id":"visual.root.session.visual.content.model[1726].url","lb":"url: Content/unit/3aw-ship_galeon_sail.mesh","tp":"str","cb":"b118"}]