[{"id":"visual.root.interface.session.nodes[11].bounds","lb":"bounds","tp":"obj","ch":[{"id":"visual.root.interface.session.nodes[11].bounds.bottomOffset","lb":"bottomOffset: 0","tp":"num","cb":"b91"},{"id":"visual.root.interface.session.nodes[11].bounds.horizontalAlign","lb":"horizontalAlign: 1","tp":"num","cb":"b91"},{"id":"visual.root.interface.session.nodes[11].bounds.leftOffset","lb":"leftOffset: 0","tp":"num","cb":"b91"},{"id":"visual.root.interface.session.nodes[11].bounds.position","lb":"position","tp":"obj","ch":[{"id":"visual.root.interface.session.nodes[11].bounds.position.x","lb":"x: 0","tp":"num","cb":"b91"},{"id":"visual.root.interface.session.nodes[11].bounds.position.y","lb":"y: 156","tp":"num","cb":"b91"}],"cb":"b91"},{"id":"visual.root.interface.session.nodes[11].bounds.rightOffset","lb":"rightOffset: 0","tp":"num","cb":"b91"},{"id":"visual.root.interface.session.nodes[11].bounds.size","lb":"size","tp":"obj","ch":[{"id":"visual.root.interface.session.nodes[11].bounds.size.x","lb":"x: 444","tp":"num","cb":"b91"},{"id":"visual.root.interface.session.nodes[11].bounds.size.y","lb":"y: 394","tp":"num","cb":"b91"}],"cb":"b91"},{"id":"visual.root.interface.session.nodes[11].bounds.topOffset","lb":"topOffset: 156","tp":"num","cb":"b91"},{"id":"visual.root.interface.session.nodes[11].bounds.verticalAlign","lb":"verticalAlign: 1","tp":"num","cb":"b91"}],"cb":"b91"},{"id":"visual.root.interface.session.nodes[11].children","lb":"children","tp":"obj","ch":[{"id":"visual.root.interface.session.nodes[11].children.f_create","lb":"f_create(type)","tp":"func","cb":"b91"},{"id":"visual.root.interface.session.nodes[11].children.f_remove","lb":"f_remove(id)","tp":"func","cb":"b91"},{"id":"visual.root.interface.session.nodes[11].children.help","lb":"help: [information]","tp":"str","cb":"b91"},{"id":"visual.root.interface.session.nodes[11].children.size","lb":"size: 0","tp":"num","cb":"b91"}],"cb":"b91"},{"id":"visual.root.interface.session.nodes[11].color","lb":"color","tp":"obj","ch":[{"id":"visual.root.interface.session.nodes[11].color.a","lb":"a: 255","tp":"num","cb":"b91"},{"id":"visual.root.interface.session.nodes[11].color.b","lb":"b: 255","tp":"num","cb":"b91"},{"id":"visual.root.interface.session.nodes[11].color.g","lb":"g: 255","tp":"num","cb":"b91"},{"id":"visual.root.interface.session.nodes[11].color.hex","lb":"hex: 0xffffffff","tp":"str","cb":"b91"},{"id":"visual.root.interface.session.nodes[11].color.r","lb":"r: 255","tp":"num","cb":"b91"},{"id":"visual.root.interface.session.nodes[11].color.value","lb":"value: 4294967295","tp":"num","cb":"b91"}],"cb":"b91"},{"id":"visual.root.interface.session.nodes[11].depth","lb":"depth: 1.0","tp":"num","cb":"b91"},{"id":"visual.root.interface.session.nodes[11].disabled","lb":"disabled: false","tp":"bool","cb":"b91"},{"id":"visual.root.interface.session.nodes[11].eventStopper","lb":"eventStopper: false","tp":"bool","cb":"b91"},{"id":"visual.root.interface.session.nodes[11].eventTransparent","lb":"eventTransparent: true","tp":"bool","cb":"b91"},{"id":"visual.root.interface.session.nodes[11].f_dockHorizontal","lb":"f_dockHorizontal(leftOffset,rightOffset)","tp":"func","cb":"b91"},{"id":"visual.root.interface.session.nodes[11].f_dockVertical","lb":"f_dockVertical(topOffset,bottomOffset)","tp":"func","cb":"b91"},{"id":"visual.root.interface.session.nodes[11].f_setBottomOffset","lb":"f_setBottomOffset(bottomOffset)","tp":"func","cb":"b91"},{"id":"visual.root.interface.session.nodes[11].f_setHorizontalAlign","lb":"f_setHorizontalAlign(align = {none = 0, left = 1, center = 2, right = 3, both = 4})","tp":"func","cb":"b91"},{"id":"visual.root.interface.session.nodes[11].f_setLeftOffset","lb":"f_setLeftOffset(leftOffset)","tp":"func","cb":"b91"},{"id":"visual.root.interface.session.nodes[11].f_setRightOffset","lb":"f_setRightOffset(rightOffset)","tp":"func","cb":"b91"},{"id":"visual.root.interface.session.nodes[11].f_setTopOffset","lb":"f_setTopOffset(topOffset)","tp":"func","cb":"b91"},{"id":"visual.root.interface.session.nodes[11].f_setVerticalAlign","lb":"f_setVerticalAlign(align = {none = 0, top = 1, center = 2, bottom = 3, both = 4})","tp":"func","cb":"b91"},{"id":"visual.root.interface.session.nodes[11].horizontalAlign","lb":"horizontalAlign: 1","tp":"num","cb":"b91"},{"id":"visual.root.interface.session.nodes[11].isFocused","lb":"isFocused: false","tp":"bool","cb":"b91"},{"id":"visual.root.interface.session.nodes[11].keepProportions","lb":"keepProportions: false","tp":"bool","cb":"b91"},{"id":"visual.root.interface.session.nodes[11].localLeft","lb":"localLeft: 0","tp":"num","cb":"b91"},{"id":"visual.root.interface.session.nodes[11].localTop","lb":"localTop: 156","tp":"num","cb":"b91"},{"id":"visual.root.interface.session.nodes[11].outOfBorder","lb":"outOfBorder: false","tp":"bool","cb":"b91"},{"id":"visual.root.interface.session.nodes[11].parent","lb":"parent: 60","tp":"num","cb":"b91"},{"id":"visual.root.interface.session.nodes[11].screenLeft","lb":"screenLeft: 0","tp":"num","cb":"b91"},{"id":"visual.root.interface.session.nodes[11].screenTop","lb":"screenTop: 156","tp":"num","cb":"b91"},{"id":"visual.root.interface.session.nodes[11].sizeX","lb":"sizeX: 444","tp":"num","cb":"b91"},{"id":"visual.root.interface.session.nodes[11].sizeY","lb":"sizeY: 394","tp":"num","cb":"b91"},{"id":"visual.root.interface.session.nodes[11].toolTipLines","lb":"toolTipLines","tp":"obj","ch":[{"id":"visual.root.interface.session.nodes[11].toolTipLines.f_clear","lb":"f_clear()","tp":"func","cb":"b91"},{"id":"visual.root.interface.session.nodes[11].toolTipLines.f_copy","lb":"f_copy(fromId, toId)","tp":"func","cb":"b91"},{"id":"visual.root.interface.session.nodes[11].toolTipLines.f_create","lb":"f_create()","tp":"func","cb":"b91"},{"id":"visual.root.interface.session.nodes[11].toolTipLines.f_insert","lb":"f_insert(index)","tp":"func","cb":"b91"},{"id":"visual.root.interface.session.nodes[11].toolTipLines.f_move","lb":"f_move(fromIndex, toIndex)","tp":"func","cb":"b91"},{"id":"visual.root.interface.session.nodes[11].toolTipLines.f_remove","lb":"f_remove(index)","tp":"func","cb":"b91"},{"id":"visual.root.interface.session.nodes[11].toolTipLines.size","lb":"size: 0","tp":"num","cb":"b91"}],"cb":"b91"},{"id":"visual.root.interface.session.nodes[11].type","lb":"type: abstract","tp":"str","cb":"b91"},{"id":"visual.root.interface.session.nodes[11].verticalAlign","lb":"verticalAlign: 1","tp":"num","cb":"b91"},{"id":"visual.root.interface.session.nodes[11].visible","lb":"visible: false","tp":"bool","cb":"b91"}]